mam/__init__.py
mam/__main__.py
mam/config.py
mam/runner.py
mam/tasks.py
mam/_mam/__init__.py
mam/_mam/keys.py
mam/_mam/config/__init__.py
mam/_mam/config/mutations/__init__.py
mam/_mam/config/mutations/tasks.py
mam/_mam/config/mutations/typings.py
mam/_mam/config/post_processing/__init__.py
mam/_mam/core/__init__.py
mam/_mam/core/configs/__init__.py
mam/_mam/core/configs/config.py
mam/_mam/core/configs/load.py
mam/_mam/core/find/__init__.py
mam/_mam/core/find/find.py
mam/_mam/core/find/object.py
mam/_mam/core/find/objects.py
mam/_mam/core/find/system.py
mam/_mam/core/objects/__init__.py
mam/_mam/core/typings/__init__.py
mam/_mam/tasks/__init__.py
mam/_mam/tasks/format/__init__.py
mam/_mam/tasks/format/formats/__init__.py
mam/_mam/tasks/format/from_str/__init__.py
mam/_mam/tasks/format/helpers/__init__.py
mam/_mam/tasks/format/to_str/__init__.py
mam/_mam/tasks/mutations/__init__.py
mam/_mam/tasks/mutations/nosa.py
mam/_mam/tasks/nox/__init__.py
mam/_mam/tasks/nox/run.py
mam/configs/bases.yaml
mam/configs/bases_new.yaml
mam/configs/default.yaml
mam-0.0.1.dist-info/LICENSE
mam-0.0.1.dist-info/METADATA
mam-0.0.1.dist-info/WHEEL
mam-0.0.1.dist-info/entry_points.txt
mam-0.0.1.dist-info/top_level.txt
mam-0.0.1.dist-info/RECORD
