Metadata-Version: 2.1
Name: mam
Version: 0.0.1
Summary: Runs linters and outputs them all together.
Home-page: https://github.com/Peilonrayz/mam
Author: Peilonrayz
Author-email: peilonrayz@gmail.com
License: MIT
Keywords: linter
Platform: UNKNOWN
Classifier: Development Status :: 3 - Alpha
Classifier: Environment :: Console
Classifier: Intended Audience :: Developers
Classifier: License :: OSI Approved :: MIT License
Classifier: Operating System :: OS Independent
Classifier: Programming Language :: Python :: 3.7
Requires-Dist: nox
Requires-Dist: PyYAML
Requires-Dist: typing-extensions
Requires-Dist: parse
Requires-Dist: mypy-extensions
